trackteroid/__init__.py
trackteroid/configuration.py
trackteroid/constants.py
trackteroid/session.py
trackteroid/entities/__init__.py
trackteroid/entities/base.py
trackteroid/entities/declarations.py
trackteroid/entities/declarations.pyi
trackteroid/entities/entities.py
trackteroid/entities/entities.pyi
trackteroid/entities/relationships_parser.py
trackteroid/entities/schematypes.py
trackteroid/query/__init__.py
trackteroid/query/criteria.py
trackteroid/query/criteria.pyi
trackteroid/query/query.py
trackteroid/query/query.pyi
trackteroid/query/utils.py
trackteroid/stubs/__init__.py
trackteroid/stubs/stubs.py
trackteroid-0.1.0rc5.dist-info/AUTHORS.md
trackteroid-0.1.0rc5.dist-info/LICENSE
trackteroid-0.1.0rc5.dist-info/METADATA
trackteroid-0.1.0rc5.dist-info/WHEEL
trackteroid-0.1.0rc5.dist-info/top_level.txt
trackteroid-0.1.0rc5.dist-info/RECORD
