Metadata-Version: 2.1
Name: trackteroid
Version: 0.1.0rc5
Summary: Declarative, object-oriented wrapper for Ftrack queries. Powerful functional-style interactions with resulting collections.
Author: Rico Koschmitzky, Dennis Weil
License: BSD 3-Clause License
Project-URL: Homepage, https://github.com/TrixterFilm/trackteroid
Project-URL: Bug Tracker, https://github.com/TrixterFilm/trackteroid/issues
Classifier: Programming Language :: Python :: 3 :: Only
Classifier: Programming Language :: Python :: 3
Classifier: Programming Language :: Python :: 3.7
Classifier: Programming Language :: Python :: 3.8
Classifier: Programming Language :: Python :: 3.9
Classifier: Programming Language :: Python :: 3.10
Classifier: Programming Language :: Python :: 3.11
Classifier: License :: OSI Approved :: BSD License
Classifier: Operating System :: OS Independent
Requires-Python: >=3.7
License-File: LICENSE
License-File: AUTHORS.md
Requires-Dist: ftrack-python-api
Requires-Dist: wrapt
